digraph v1 {
	node [shape=box]

	0 [label="   0: iload_0[26](1)"];
	0 -> 1;
	13 [label="  13: invokevirtual[182](3) 24"];
	13 -> 16;
	5 [label="   5: ifne[154](3) -> iload_0"];
	5 -> 8;
	5 -> 19;
	60 [label="  60: iload_0[26](1)"];
	60 -> 61;
	23 [label="  23: getstatic[178](3) 16"];
	23 -> 26;
	28 [label="  28: idiv[108](1)"];
	28 -> 29;
	48 [label="  48: goto[167](3) -> return"];
	48 -> 77;
	39 [label="  39: getstatic[178](3) 16"];
	39 -> 42;
	45 [label="  45: invokevirtual[182](3) 30"];
	45 -> 48;
	61 [label="  61: idiv[108](1)"];
	61 -> 62;
	35 [label="  35: iload_1[27](1)"];
	35 -> 36;
	53 [label="  53: if_icmpge[162](3) -> getstatic 16"];
	53 -> 56;
	53 -> 68;
	11 [label="  11: ldc[18](2) 22"];
	11 -> 13;
	77 [label="  77: return[177](1)"];
	4 [label="   4: iload_1[27](1)"];
	4 -> 5;
	72 [label="  72: iload_1[27](1)"];
	72 -> 73;
	43 [label="  43: iload_0[26](1)"];
	43 -> 44;
	19 [label="  19: iload_0[26](1)"];
	19 -> 20;
	42 [label="  42: iload_1[27](1)"];
	42 -> 43;
	73 [label="  73: idiv[108](1)"];
	73 -> 74;
	16 [label="  16: goto[167](3) -> return"];
	16 -> 77;
	71 [label="  71: iload_0[26](1)"];
	71 -> 72;
	56 [label="  56: getstatic[178](3) 16"];
	56 -> 59;
	51 [label="  51: iload_0[26](1)"];
	51 -> 52;
	27 [label="  27: iload_1[27](1)"];
	27 -> 28;
	68 [label="  68: getstatic[178](3) 16"];
	68 -> 71;
	52 [label="  52: iload_1[27](1)"];
	52 -> 53;
	65 [label="  65: goto[167](3) -> return"];
	65 -> 77;
	59 [label="  59: iload_1[27](1)"];
	59 -> 60;
	29 [label="  29: invokevirtual[182](3) 30"];
	29 -> 32;
	44 [label="  44: idiv[108](1)"];
	44 -> 45;
	8 [label="   8: getstatic[178](3) 16"];
	8 -> 11;
	62 [label="  62: invokevirtual[182](3) 30"];
	62 -> 65;
	20 [label="  20: ifne[154](3) -> iload_1"];
	20 -> 23;
	20 -> 35;
	1 [label="   1: ifne[154](3) -> iload_0"];
	1 -> 4;
	1 -> 19;
	74 [label="  74: invokevirtual[182](3) 30"];
	74 -> 77;
	26 [label="  26: iload_0[26](1)"];
	26 -> 27;
	32 [label="  32: goto[167](3) -> return"];
	32 -> 77;
	36 [label="  36: ifne[154](3) -> iload_0"];
	36 -> 39;
	36 -> 51;
}